recipe_database_scraper/__init__.py
recipe_database_scraper/_exceptions.py
recipe_database_scraper/_utils.py
recipe_database_scraper/get_html.py
recipe_database_scraper/recipe_scraper.py
recipe_database_scraper/sitemap_scraper.py
recipe_database_scraper-0.2.0.dist-info/METADATA
recipe_database_scraper-0.2.0.dist-info/WHEEL
recipe_database_scraper-0.2.0.dist-info/RECORD
