Metadata-Version: 2.1
Name: recipe-database-scraper
Version: 0.2.0
Summary: Python package for building and maintaining a recipe database by scraping a base url
Home-page: https://github.com/jaspervzwi/recipe-database-scraper
License: MIT
Keywords: recipe,scraper,web scraping,recipes,database
Author: jaspervzwi
Author-email: jasperzwieten@gmail.com
Requires-Python: >=3.9,<4.0
Classifier: License :: OSI Approved :: MIT License
Classifier: Programming Language :: Python :: 3
Classifier: Programming Language :: Python :: 3.9
Classifier: Programming Language :: Python :: 3.10
Classifier: Programming Language :: Python :: 3.11
Classifier: Programming Language :: Python :: 3.12
Requires-Dist: publicsuffix2 (>=2.20191221,<3.0)
Requires-Dist: recipe-scrapers (>=15.2.1,<16.0.0)
Requires-Dist: requests (>=2.32.3,<3.0.0)
Requires-Dist: robotspy (>=0.10.0,<0.11.0)
Requires-Dist: ultimate-sitemap-parser (>=0.5,<0.6)
Project-URL: Repository, https://github.com/jaspervzwi/recipe-database-scraper
